neuralgc/__init__.py
neuralgc/synthetic.py
neuralgc/models/__init__.py
neuralgc/models/clstm.py
neuralgc/models/cmlp.py
neuralgc/models/crnn.py
neuralgc/models/model_helper.py
neuralgc-0.0.1.dist-info/METADATA
neuralgc-0.0.1.dist-info/WHEEL
neuralgc-0.0.1.dist-info/licenses/LICENSE
neuralgc-0.0.1.dist-info/RECORD
