Metadata-Version: 2.4
Name: neuralgc
Version: 0.0.1
Summary: Neural Granger Causality
License-File: LICENSE
Requires-Python: >=3.8
Requires-Dist: ipykernel>=6.29.5
Requires-Dist: matplotlib
Requires-Dist: numpy
Requires-Dist: scipy
Requires-Dist: torch
